{
  "$schema": "https://vega.github.io/schema/vega-lite/v5.json",

  "width": 280,
  "height": 220,

  "data": {
    "url": "data/raw/telecommunications_statistics_malaysia.csv"
  },

  "transform": [
    {
      "filter": "datum.Items == 'Number of Cellular phones subscriptions'"
    },
    {
      "filter": "datum.SubItems == 'Post paid' || datum.SubItems == 'Prepaid'"
    }
  ],

  "mark": {
    "type": "line",
    "point": true
  },

  "encoding": {
    "x": {
      "field": "Year",
      "type": "quantitative"
    },

    "y": {
      "field": "Value",
      "type": "quantitative",
      "scale": {
        "domainMin": 0
      }
    },

    "color": {
      "field": "SubItems",
      "type": "nominal"
    }
  }
}
